typing_speed_test_abdalrahman_v2/__init__.py
typing_speed_test_abdalrahman_v2/main.py
typing_speed_test_abdalrahman_v2-1.0.0.dist-info/licenses/LICENSE
typing_speed_test_abdalrahman_v2-1.0.0.dist-info/METADATA
typing_speed_test_abdalrahman_v2-1.0.0.dist-info/WHEEL
typing_speed_test_abdalrahman_v2-1.0.0.dist-info/entry_points.txt
typing_speed_test_abdalrahman_v2-1.0.0.dist-info/top_level.txt
typing_speed_test_abdalrahman_v2-1.0.0.dist-info/RECORD
