Metadata-Version: 2.4
Name: typing_speed_test_abdalrahman_v2
Version: 1.0.0
Summary: A simple typing speed test game in Python
Home-page: https://github.com/abdalrahman_wahas23/typing_speed_test_abdalrahman_v2
Author: Abdalrahman Wahas
Author-email: your_email@example.com
Classifier: Programming Language :: Python :: 3
Classifier: License :: OSI Approved :: MIT License
Classifier: Operating System :: OS Independent
Requires-Python: >=3.6
License-File: LICENSE
Dynamic: author
Dynamic: author-email
Dynamic: classifier
Dynamic: description
Dynamic: description-content-type
Dynamic: home-page
Dynamic: license-file
Dynamic: requires-python
Dynamic: summary
